{
    "Timestamp": [
        "2024-09-13 13:13:46",
        "2024-09-13 13:13:48"
    ],
    "Roll": [
        -0.7172070020049508,
        -0.752637114220511
    ],
    "Pitch": [
        0.7049086060741081,
        0.7274500979650014
    ],
    "Yaw": [
        20.574759836842414,
        20.76895577532422
    ],
    "Latitude": [
        0.0,
        0.0
    ],
    "Longitude": [
        0.0,
        0.0
    ],
    "Altitude": [
        -17.0,
        -17.0
    ],
    "HDOP": [
        99.99,
        99.99
    ],
    "VDOP": [
        99.99,
        99.99
    ],
    "Satellites": [
        0,
        0
    ],
    "Flight_Mode": [
        "STABILIZE",
        "STABILIZE"
    ],
    "Voltage": [
        4.642,
        4.637
    ],
    "Current": [
        13.39,
        13.43
    ],
    "Armed": [
        false,
        false
    ]
}