{
    "Timestamp": [
        "2024-09-16 19:37:59",
        "2024-09-16 19:38:01",
        "2024-09-16 19:38:03",
        "2024-09-16 19:38:05",
        "2024-09-16 19:38:07",
        "2024-09-16 19:38:09",
        "2024-09-16 19:38:11"
    ],
    "Roll": [
        -0.42754550949388004,
        -0.41230757089899317,
        -0.3723558734528845,
        -0.380498312717186,
        -0.38561263030164455,
        -0.3873197507073246,
        -0.4237985104038934
    ],
    "Pitch": [
        1.197475275310688,
        1.1887347676071875,
        1.1633585871281802,
        1.1609412337705247,
        1.159976576271966,
        1.167966937105529,
        1.1811272175322627
    ],
    "Yaw": [
        14.316477773960465,
        14.666719629314963,
        14.882247956122008,
        14.828979310785078,
        14.801498044659532,
        14.750346757965307,
        14.694182112420291
    ],
    "Latitude": [
        0.0,
        0.0,
        0.0,
        0.0,
        0.0,
        0.0,
        0.0
    ],
    "Longitude": [
        0.0,
        0.0,
        0.0,
        0.0,
        0.0,
        0.0,
        0.0
    ],
    "Altitude": [
        -17.0,
        -17.0,
        -17.0,
        -17.0,
        -17.0,
        -17.0,
        -17.0
    ],
    "HDOP": [
        99.99,
        99.99,
        99.99,
        99.99,
        99.99,
        99.99,
        99.99
    ],
    "VDOP": [
        99.99,
        99.99,
        99.99,
        99.99,
        99.99,
        99.99,
        99.99
    ],
    "Satellites": [
        0,
        0,
        0,
        0,
        0,
        0,
        0
    ],
    "Flight_Mode": [
        "STABILIZE",
        "STABILIZE",
        "STABILIZE",
        "STABILIZE",
        "STABILIZE",
        "STABILIZE",
        "STABILIZE"
    ],
    "Voltage": [
        4.718,
        4.739,
        4.728,
        4.729,
        4.723,
        4.732,
        4.732
    ],
    "Current": [
        13.44,
        13.66,
        13.55,
        13.56,
        13.53,
        13.61,
        13.62
    ],
    "Armed": [
        false,
        false,
        false,
        false,
        false,
        false,
        false
    ]
}